pypn_habref_api/__init__.py
pypn_habref_api/env.py
pypn_habref_api/models.py
pypn_habref_api/routes.py
pypn_habref_api/schemas.py
pypn_habref_api/data/__init__.py
pypn_habref_api/data/data_inpn_habref.sql
pypn_habref_api/data/habref.sql
pypn_habref_api/migrations/__init__.py
pypn_habref_api/migrations/env.py
pypn_habref_api/migrations/versions/46e91e738845_insert_inpn_data_in_ref_habitats_schema.py
pypn_habref_api/migrations/versions/62e63cd6135d_create_ref_habitats_schema.py
pypn_habref_api/migrations/versions/805442837a68_correction_on_habref_data.py
pypn_habref_api/migrations/versions/__init__.py
pypn_habref_api/tests/__init__.py
pypn_habref_api/tests/conftest.py
pypn_habref_api/tests/fixtures.py
pypn_habref_api/tests/test_habref.py
pypn_habref_api-0.4.3.dist-info/licenses/LICENSE
pypn_habref_api-0.4.3.dist-info/METADATA
pypn_habref_api-0.4.3.dist-info/WHEEL
pypn_habref_api-0.4.3.dist-info/entry_points.txt
pypn_habref_api-0.4.3.dist-info/top_level.txt
pypn_habref_api-0.4.3.dist-info/RECORD
