Metadata-Version: 2.4
Name: pypn_habref_api
Version: 0.4.3
Summary: Python lib related to Habref referential (INPN)
Home-page: https://github.com/PnX-SI/Habref-api-module
Maintainer: Parcs nationaux des Écrins et des Cévennes
Maintainer-email: geonature@ecrins-parcnational.fr
Classifier: Development Status :: 1 - Planning
Classifier: Intended Audience :: Developers
Classifier: Natural Language :: English
Classifier: Programming Language :: Python :: 3.9
Classifier: Programming Language :: Python :: 3.11
Classifier: License :: OSI Approved :: GNU Affero General Public License v3
Classifier: Operating System :: OS Independent
License-File: LICENSE
Requires-Dist: python-dotenv
Requires-Dist: flask
Requires-Dist: flask-marshmallow
Requires-Dist: flask-sqlalchemy
Requires-Dist: flask-migrate
Requires-Dist: marshmallow-sqlalchemy
Requires-Dist: marshmallow
Requires-Dist: psycopg2
Requires-Dist: requests
Requires-Dist: utils-flask-sqlalchemy>=0.4.1
Requires-Dist: sqlalchemy<2
Provides-Extra: tests
Requires-Dist: pytest; extra == "tests"
Requires-Dist: pytest-flask; extra == "tests"
Dynamic: classifier
Dynamic: description
Dynamic: description-content-type
Dynamic: home-page
Dynamic: license-file
Dynamic: maintainer
Dynamic: maintainer-email
Dynamic: provides-extra
Dynamic: requires-dist
Dynamic: summary
